Workbook

Sheet Parâmetros
A1: Parâmetro | B1: Valor
A2: Aporte Inicial | B2: 1000000
A3: Aportes Anuais | B3: 0
A4: Horizonte em anos | B4: 30
A5: Taxa nominal esperada ao ano (%) | B5: 10
A6: Inflação esperada (%) | B6: 4
A7: Giro da carteira (%) | B7: 20
A8: Percentual de distribuição de dividendos anuais (%) | B8: 50
A9: Dividendos recebidos por ano (inicial) | B9: 1200000
A10: Alíquota adicional de IRPF no ajuste sobre dividendos (%) | B10: 10
A11: Alíquota efetiva PF sobre rendimentos (%) | B11: 15
A12: Alíquota efetiva PJ sobre rendimentos (%) | B12: 34
A13: Alíquota sobre distribuição da PJ para PF (%) | B13: 0
... A20: Taxa de desconto para valor presente (%) | B20: 8

Sheet Cálculo PF
A1: Ano | B1: Saldo Inicial | C1: Rendimento Bruto | D1: Impostos | E1: Ajuste Adicional de 10% sobre dividendos | F1: Rendimento Líquido | G1: Reinvestimento | H1: Saldo Final
A2: 1 | B2: =Parâmetros!B2 | C2: =B2 * Parâmetros!B5 / 100 | D2: =C2 * Parâmetros!B11 / 100 | E2: =(C2 * Parâmetros!B8 / 100) * Parâmetros!B10 / 100 | F2: 0 | G2: =F2 * Parâmetros!B19 / 100 | H2: =B2 + G2 + Parâmetros!B3
A3: 2 | B3: =H2 + Parâmetros!B3 | C3: =B3 * Parâmetros!B5 / 100 | D3: =C3 * Parâmetros!B11 / 100 | E3: =(C3 * Parâmetros!B8 / 100) * Parâmetros!B10 / 100 | F3: 0 | G3: =F3 * Parâmetros!B19 / 100 | H3: =B3 + G3 + Parâmetros!B3
A4: 3 | B4: =H3 + Parâmetros!B3 | C4: =B4 * Parâmetros!B5 / 100 | D4: =C4 * Parâmetros!B11 / 100 | E4: =(C4 * Parâmetros!B8 / 100) * Parâmetros!B10 / 100 | F4: 0 | G4: =F4 * Parâmetros!B19 / 100 | H4: =B4 + G4 + Parâmetros!B3
A5: 4 | B5: =H4 + Parâmetros!B3 | C5: =B5 * Parâmetros!B5 / 100 | D5: =C5 * Parâmetros!B11 / 100 | E5: =(C5 * Parâmetros!B8 / 100) * Parâmetros!B10 / 100 | F5: 0 | G5: =F5 * Parâmetros!B19 / 100 | H5: =B5 + G5 + Parâmetros!B3
A6: 5 | B6: =H5 + Parâmetros!B3 | C6: =B6 * Parâmetros!B5 / 100 | D6: =C6 * Parâmetros!B11 / 100 | E6: =(C6 * Parâmetros!B8 / 100) * Parâmetros!B10 / 100 | F6: 0 | G6: =F6 * Parâmetros!B19 / 100 | H6: =B6 + G6 + Parâmetros!B3
A7: 6 | B7: =H6 + Parâmetros!B3 | C7: =B7 * Parâmetros!B5 / 100 | D7: =C7 * Parâmetros!B11 / 100 | E7: =(C7 * Parâmetros!B8 / 100) * Parâmetros!B10 / 100 | F7: 0 | G7: =F7 * Parâmetros!B19 / 100 | H7: =B7 + G7 + Parâmetros!B3
A8: 7 | B8: =H7 + Parâmetros!B3 | C8: =B8 * Parâmetros!B5 / 100 | D8: =C8 * Parâmetros!B11 / 100 | E8: =(C8 * Parâmetros!B8 / 100) * Parâmetros!B10 / 100 | F8: 0 | G8: =F8 * Parâmetros!B19 / 100 | H8: =B8 + G8 + Parâmetros!B3
A9: 8 | B9: =H8 + Parâmetros!B3 | C9: =B9 * Parâmetros!B5 / 100 | D9: =C9 * Parâmetros!B11 / 100 | E9: =(C9 * Parâmetros!B8 / 100) * Parâmetros!B10 / 100 | F9: 0 | G9: =F9 * Parâmetros!B19 / 100 | H9: =B9 + G9 + Parâmetros!B3
A10: 9 | B10: =H9 + Parâmetros!B3 | C10: =B10 * Parâmetros!B5 / 100 | D10: =C10 * Parâmetros!B11 / 100 | E10: =(C10 * Parâmetros!B8 / 100) * Parâmetros!B10 / 100 | F10: 0 | G10: =F10 * Parâmetros!B19 / 100 | H10: =B10 + G10 + Parâmetros!B3
A11: 10 | B11: =H10 + Parâmetros!B3 | C11: =B11 * Parâmetros!B5 / 100 | D11: =C11 * Parâmetros!B11 / 100 | E11: =(C11 * Parâmetros!B8 / 100) * Parâmetros!B10 / 100 | F11: 0 | G11: =F11 * Parâmetros!B19 / 100 | H11: =B11 + G11 + Parâmetros!B3
A12: 11 | B12: =H11 + Parâmetros!B3 | C12: =B12 * Parâmetros!B5 / 100 | D12: =C12 * Parâmetros!B11 / 100 | E12: =(C12 * Parâmetros!B8 / 100) * Parâmetros!B10 / 100 | F12: 0 | G12: =F12 * Parâmetros!B19 / 100 | H12: =B12 + G12 + Parâmetros!B3
A13: 12 | B13: =H12 + Parâmetros!B3 | C13: =B13 * Parâmetros!B5 / 100 | D13: =C13 * Parâmetros!B11 / 100 | E13: =(C13 * Parâmetros!B8 / 100) * Parâmetros!B10 / 100 | F13: 0 | G13: =F13 * Parâmetros!B19 / 100 | H13: =B13 + G13 + Parâmetros!B3
A14: 13 | B14: =H13 + Parâmetros!B3 | C14: =B14 * Parâmetros!B5 / 100 | D14: =C14 * Parâmetros!B11 / 100 | E14: =(C14 * Parâmetros!B8 / 100) * Parâmetros!B10 / 100 | F14: 0 | G14: =F14 * Parâmetros!B19 / 100 | H14: =B14 + G14 + Parâmetros!B3
A15: 14 | B15: =H14 + Parâmetros!B3 | C15: =B15 * Parâmetros!B5 / 100 | D15: =C15 * Parâmetros!B11 / 100 | E15: =(C15 * Parâmetros!B8 / 100) * Parâmetros!B10 / 100 | F15: 0 | G15: =F15 * Parâmetros!B19 / 100 | H15: =B15 + G15 + Parâmetros!B3
A16: 15 | B16: =H15 + Parâmetros!B3 | C16: =B16 * Parâmetros!B5 / 100 | D16: =C16 * Parâmetros!B11 / 100 | E16: =(C16 * Parâmetros!B8 / 100) * Parâmetros!B10 / 100 | F16: 0 | G16: =F16 * Parâmetros!B19 / 100 | H16: =B16 + G16 + Parâmetros!B3
A17: 16 | B17: =H16 + Parâmetros!B3 | C17: =B17 * Parâmetros!B5 / 100 | D17: =C17 * Parâmetros!B11 / 100 | E17: =(C17 * Parâmetros!B8 / 100) * Parâmetros!B10 / 100 | F17: 0 | G17: =F17 * Parâmetros!B19 / 100 | H17: =B17 + G17 + Parâmetros!B3
A18: 17 | B18: =H17 + Parâmetros!B3 | C18: =B18 * Parâmetros!B5 / 100 | D18: =C18 * Parâmetros!B11 / 100 | E18: =(C18 * Parâmetros!B8 / 100) * Parâmetros!B10 / 100 | F18: 0 | G18: =F18 * Parâmetros!B19 / 100 | H18: =B18 + G18 + Parâmetros!B3
A19: 18 | B19: =H18 + Parâmetros!B3 | C19: =B19 * Parâmetros!B5 / 100 | D19: =C19 * Parâmetros!B11 / 100 | E19: =(C19 * Parâmetros!B8 / 100) * Parâmetros!B10 / 100 | F19: 0 | G19: =F19 * Parâmetros!B19 / 100 | H19: =B19 + G19 + Parâmetros!B3
A20: 19 | B20: =H19 + Parâmetros!B3 | C20: =B20 * Parâmetros!B5 / 100 | D20: =C20 * Parâmetros!B11 / 100 | E20: =(C20 * Parâmetros!B8 / 100) * Parâmetros!B10 / 100 | F20: 0 | G20: =F20 * Parâmetros!B19 / 100 | H20: =B20 + G20 + Parâmetros!B3
A21: 20 | B21: =H20 + Parâmetros!B3 | C21: =B21 * Parâmetros!B5 / 100 | D21: =C21 * Parâmetros!B11 / 100 | E21: =(C21 * Parâmetros!B8 / 100) * Parâmetros!B10 / 100 | F21: 0 | G21: =F21 * Parâmetros!B19 / 100 | H21: =B21 + G21 + Parâmetros!B3
A22: 21 | B22: =H21 + Parâmetros!B3 | C22: =B22 * Parâmetros!B5 / 100 | D22: =C22 * Parâmetros!B11 / 100 | E22: =(C22 * Parâmetros!B8 / 100) * Parâmetros!B10 / 100 | F22: 0 | G22: =F22 * Parâmetros!B19 / 100 | H22: =B22 + G22 + Parâmetros!B3
A23: 22 | B23: =H22 + Parâmetros!B3 | C23: =B23 * Parâmetros!B5 / 100 | D23: =C23 * Parâmetros!B11 / 100 | E23: =(C23 * Parâmetros!B8 / 100) * Parâmetros!B10 / 100 | F23: 0 | G23: =F23 * Parâmetros!B19 / 100 | H23: =B23 + G23 + Parâmetros!B3
A24: 23 | B24: =H23 + Parâmetros!B3 | C24: =B24 * Parâmetros!B5 / 100 | D24: =C24 * Parâmetros!B11 / 100 | E24: =(C24 * Parâmetros!B8 / 100) * Parâmetros!B10 / 100 | F24: 0 | G24: =F24 * Parâmetros!B19 / 100 | H24: =B24 + G24 + Parâmetros!B3
A25: 24 | B25: =H24 + Parâmetros!B3 | C25: =B25 * Parâmetros!B5 / 100 | D25: =C25 * Parâmetros!B11 / 100 | E25: =(C25 * Parâmetros!B8 / 100) * Parâmetros!B10 / 100 | F25: 0 | G25: =F25 * Parâmetros!B19 / 100 | H25: =B25 + G25 + Parâmetros!B3
A26: 25 | B26: =H25 + Parâmetros!B3 | C26: =B26 * Parâmetros!B5 / 100 | D26: =C26 * Parâmetros!B11 / 100 | E26: =(C26 * Parâmetros!B8 / 100) * Parâmetros!B10 / 100 | F26: 0 | G26: =F26 * Parâmetros!B19 / 100 | H26: =B26 + G26 + Parâmetros!B3
A27: 26 | B27: =H26 + Parâmetros!B3 | C27: =B27 * Parâmetros!B5 / 100 | D27: =C27 * Parâmetros!B11 / 100 | E27: =(C27 * Parâmetros!B8 / 100) * Parâmetros!B10 / 100 | F27: 0 | G27: =F27 * Parâmetros!B19 / 100 | H27: =B27 + G27 + Parâmetros!B3
A28: 27 | B28: =H27 + Parâmetros!B3 | C28: =B28 * Parâmetros!B5 / 100 | D28: =C28 * Parâmetros!B11 / 100 | E28: =(C28 * Parâmetros!B8 / 100) * Parâmetros!B10 / 100 | F28: 0 | G28: =F28 * Parâmetros!B19 / 100 | H28: =B28 + G28 + Parâmetros!B3
A29: 28 | B29: =H28 + Parâmetros!B3 | C29: =B29 * Parâmetros!B5 / 100 | D29: =C29 * Parâmetros!B11 / 100 | E29: =(C29 * Parâmetros!B8 / 100) * Parâmetros!B10 / 100 | F29: 0 | G29: =F29 * Parâmetros!B19 / 100 | H29: =B29 + G29 + Parâmetros!B3
A30: 29 | B30: =H29 + Parâmetros!B3 | C30: =B30 * Parâmetros!B5 / 100 | D30: =C30 * Parâmetros!B11 / 100 | E30: =(C30 * Parâmetros!B8 / 100) * Parâmetros!B10 / 100 | F30: 0 | G30: =F30 * Parâmetros!B19 / 100 | H30: =B30 + G30 + Parâmetros!B3
A31: 30 | B31: =H30 + Parâmetros!B3 | C31: =B31 * Parâmetros!B5 / 100 | D31: =C31 * Parâmetros!B11 / 100 | E31: =(C31 * Parâmetros!B8 / 100) * Parâmetros!B10 / 100 | F31: 0 | G31: =F31 * Parâmetros!B19 / 100 | H31: =B31 + G31 + Parâmetros!B3

Sheet Cálculo PJ
A1: Ano | B1: Saldo Inicial | C1: Rendimento Bruto | D1: IRPJ/CSLL Efetivo | E1: Custos da Holding | F1: Lucro Líquido PJ | G1: Distribuição | H1: Tributação na Saída para PF | I1: Líquido para PF | J1: Reinvestimento em PJ | K1: Saldo Final
A2: 1 | B2: =Parâmetros!B2 | C2: =B2 * Parâmetros!B5 / 100 | D2: =C2 * Parâmetros!B12 / 100 | E2: =Parâmetros!B14 + Parâmetros!B15 | F2: 0 | G2: =IF(F2>0, F2 * Parâmetros!B8 / 100, 0) | H2: =G2 * Parâmetros!B13 / 100 | I2: 0 | J2: =IF(F2>0, F2 - G2, 0) | K2: =B2 + J2 + Parâmetros!B3
A3: 2 | B3: =K2 + Parâmetros!B3 | C3: =B3 * Parâmetros!B5 / 100 | D3: =C3 * Parâmetros!B12 / 100 | E3: =Parâmetros!B14 + Parâmetros!B15 | F3: 0 | G3: =IF(F3>0, F3 * Parâmetros!B8 / 100, 0) | H3: =G3 * Parâmetros!B13 / 100 | I3: 0 | J3: =IF(F3>0, F3 - G3, 0) | K3: =B3 + J3 + Parâmetros!B3
A4: 3 | B4: =K3 + Parâmetros!B3 | C4: =B4 * Parâmetros!B5 / 100 | D4: =C4 * Parâmetros!B12 / 100 | E4: =Parâmetros!B14 + Parâmetros!B15 | F4: 0 | G4: =IF(F4>0, F4 * Parâmetros!B8 / 100, 0) | H4: =G4 * Parâmetros!B13 / 100 | I4: 0 | J4: =IF(F4>0, F4 - G4, 0) | K4: =B4 + J4 + Parâmetros!B3
A5: 4 | B5: =K4 + Parâmetros!B3 | C5: =B5 * Parâmetros!B5 / 100 | D5: =C5 * Parâmetros!B12 / 100 | E5: =Parâmetros!B14 + Parâmetros!B15 | F5: 0 | G5: =IF(F5>0, F5 * Parâmetros!B8 / 100, 0) | H5: =G5 * Parâmetros!B13 / 100 | I5: 0 | J5: =IF(F5>0, F5 - G5, 0) | K5: =B5 + J5 + Parâmetros!B3
A6: 5 | B6: =K5 + Parâmetros!B3 | C6: =B6 * Parâmetros!B5 / 100 | D6: =C6 * Parâmetros!B12 / 100 | E6: =Parâmetros!B14 + Parâmetros!B15 | F6: 0 | G6: =IF(F6>0, F6 * Parâmetros!B8 / 100, 0) | H6: =G6 * Parâmetros!B13 / 100 | I6: 0 | J6: =IF(F6>0, F6 - G6, 0) | K6: =B6 + J6 + Parâmetros!B3
A7: 6 | B7: =K6 + Parâmetros!B3 | C7: =B7 * Parâmetros!B5 / 100 | D7: =C7 * Parâmetros!B12 / 100 | E7: =Parâmetros!B14 + Parâmetros!B15 | F7: 0 | G7: =IF(F7>0, F7 * Parâmetros!B8 / 100, 0) | H7: =G7 * Parâmetros!B13 / 100 | I7: 0 | J7: =IF(F7>0, F7 - G7, 0) | K7: =B7 + J7 + Parâmetros!B3
A8: 7 | B8: =K7 + Parâmetros!B3 | C8: =B8 * Parâmetros!B5 / 100 | D8: =C8 * Parâmetros!B12 / 100 | E8: =Parâmetros!B14 + Parâmetros!B15 | F8: 0 | G8: =IF(F8>0, F8 * Parâmetros!B8 / 100, 0) | H8: =G8 * Parâmetros!B13 / 100 | I8: 0 | J8: =IF(F8>0, F8 - G8, 0) | K8: =B8 + J8 + Parâmetros!B3
A9: 8 | B9: =K8 + Parâmetros!B3 | C9: =B9 * Parâmetros!B5 / 100 | D9: =C9 * Parâmetros!B12 / 100 | E9: =Parâmetros!B14 + Parâmetros!B15 | F9: 0 | G9: =IF(F9>0, F9 * Parâmetros!B8 / 100, 0) | H9: =G9 * Parâmetros!B13 / 100 | I9: 0 | J9: =IF(F9>0, F9 - G9, 0) | K9: =B9 + J9 + Parâmetros!B3
A10: 9 | B10: =K9 + Parâmetros!B3 | C10: =B10 * Parâmetros!B5 / 100 | D10: =C10 * Parâmetros!B12 / 100 | E10: =Parâmetros!B14 + Parâmetros!B15 | F10: 0 | G10: =IF(F10>0, F10 * Parâmetros!B8 / 100, 0) | H10: =G10 * Parâmetros!B13 / 100 | I10: 0 | J10: =IF(F10>0, F10 - G10, 0) | K10: =B10 + J10 + Parâmetros!B3
A11: 10 | B11: =K10 + Parâmetros!B3 | C11: =B11 * Parâmetros!B5 / 100 | D11: =C11 * Parâmetros!B12 / 100 | E11: =Parâmetros!B14 + Parâmetros!B15 | F11: 0 | G11: =IF(F11>0, F11 * Parâmetros!B8 / 100, 0) | H11: =G11 * Parâmetros!B13 / 100 | I11: 0 | J11: =IF(F11>0, F11 - G11, 0) | K11: =B11 + J11 + Parâmetros!B3
A12: 11 | B12: =K11 + Parâmetros!B3 | C12: =B12 * Parâmetros!B5 / 100 | D12: =C12 * Parâmetros!B12 / 100 | E12: =Parâmetros!B14 + Parâmetros!B15 | F12: 0 | G12: =IF(F12>0, F12 * Parâmetros!B8 / 100, 0) | H12: =G12 * Parâmetros!B13 / 100 | I12: 0 | J12: =IF(F12>0, F12 - G12, 0) | K12: =B12 + J12 + Parâmetros!B3
A13: 12 | B13: =K12 + Parâmetros!B3 | C13: =B13 * Parâmetros!B5 / 100 | D13: =C13 * Parâmetros!B12 / 100 | E13: =Parâmetros!B14 + Parâmetros!B15 | F13: 0 | G13: =IF(F13>0, F13 * Parâmetros!B8 / 100, 0) | H13: =G13 * Parâmetros!B13 / 100 | I13: 0 | J13: =IF(F13>0, F13 - G13, 0) | K13: =B13 + J13 + Parâmetros!B3
A14: 13 | B14: =K13 + Parâmetros!B3 | C14: =B14 * Parâmetros!B5 / 100 | D14: =C14 * Parâmetros!B12 / 100 | E14: =Parâmetros!B14 + Parâmetros!B15 | F14: 0 | G14: =IF(F14>0, F14 * Parâmetros!B8 / 100, 0) | H14: =G14 * Parâmetros!B13 / 100 | I14: 0 | J14: =IF(F14>0, F14 - G14, 0) | K14: =B14 + J14 + Parâmetros!B3
A15: 14 | B15: =K14 + Parâmetros!B3 | C15: =B15 * Parâmetros!B5 / 100 | D15: =C15 * Parâmetros!B12 / 100 | E15: =Parâmetros!B14 + Parâmetros!B15 | F15: 0 | G15: =IF(F15>0, F15 * Parâmetros!B8 / 100, 0) | H15: =G15 * Parâmetros!B13 / 100 | I15: 0 | J15: =IF(F15>0, F15 - G15, 0) | K15: =B15 + J15 + Parâmetros!B3
A16: 15 | B16: =K15 + Parâmetros!B3 | C16: =B16 * Parâmetros!B5 / 100 | D16: =C16 * Parâmetros!B12 / 100 | E16: =Parâmetros!B14 + Parâmetros!B15 | F16: 0 | G16: =IF(F16>0, F16 * Parâmetros!B8 / 100, 0) | H16: =G16 * Parâmetros!B13 / 100 | I16: 0 | J16: =IF(F16>0, F16 - G16, 0) | K16: =B16 + J16 + Parâmetros!B3
A17: 16 | B17: =K16 + Parâmetros!B3 | C17: =B17 * Parâmetros!B5 / 100 | D17: =C17 * Parâmetros!B12 / 100 | E17: =Parâmetros!B14 + Parâmetros!B15 | F17: 0 | G17: =IF(F17>0, F17 * Parâmetros!B8 / 100, 0) | H17: =G17 * Parâmetros!B13 / 100 | I17: 0 | J17: =IF(F17>0, F17 - G17, 0) | K17: =B17 + J17 + Parâmetros!B3
A18: 17 | B18: =K17 + Parâmetros!B3 | C18: =B18 * Parâmetros!B5 / 100 | D18: =C18 * Parâmetros!B12 / 100 | E18: =Parâmetros!B14 + Parâmetros!B15 | F18: 0 | G18: =IF(F18>0, F18 * Parâmetros!B8 / 100, 0) | H18: =G18 * Parâmetros!B13 / 100 | I18: 0 | J18: =IF(F18>0, F18 - G18, 0) | K18: =B18 + J18 + Parâmetros!B3
A19: 18 | B19: =K18 + Parâmetros!B3 | C19: =B19 * Parâmetros!B5 / 100 | D19: =C19 * Parâmetros!B12 / 100 | E19: =Parâmetros!B14 + Parâmetros!B15 | F19: 0 | G19: =IF(F19>0, F19 * Parâmetros!B8 / 100, 0) | H19: =G19 * Parâmetros!B13 / 100 | I19: 0 | J19: =IF(F19>0, F19 - G19, 0) | K19: =B19 + J19 + Parâmetros!B3
A20: 19 | B20: =K19 + Parâmetros!B3 | C20: =B20 * Parâmetros!B5 / 100 | D20: =C20 * Parâmetros!B12 / 100 | E20: =Parâmetros!B14 + Parâmetros!B15 | F20: 0 | G20: =IF(F20>0, F20 * Parâmetros!B8 / 100, 0) | H20: =G20 * Parâmetros!B13 / 100 | I20: 0 | J20: =IF(F20>0, F20 - G20, 0) | K20: =B20 + J20 + Parâmetros!B3
A21: 20 | B21: =K20 + Parâmetros!B3 | C21: =B21 * Parâmetros!B5 / 100 | D21: =C21 * Parâmetros!B12 / 100 | E21: =Parâmetros!B14 + Parâmetros!B15 | F21: 0 | G21: =IF(F21>0, F21 * Parâmetros!B8 / 100, 0) | H21: =G21 * Parâmetros!B13 / 100 | I21: 0 | J21: =IF(F21>0, F21 - G21, 0) | K21: =B21 + J21 + Parâmetros!B3
A22: 21 | B22: =K21 + Parâmetros!B3 | C22: =B22 * Parâmetros!B5 / 100 | D22: =C22 * Parâmetros!B12 / 100 | E22: =Parâmetros!B14 + Parâmetros!B15 | F22: 0 | G22: =IF(F22>0, F22 * Parâmetros!B8 / 100, 0) | H22: =G22 * Parâmetros!B13 / 100 | I22: 0 | J22: =IF(F22>0, F22 - G22, 0) | K22: =B22 + J22 + Parâmetros!B3
A23: 22 | B23: =K22 + Parâmetros!B3 | C23: =B23 * Parâmetros!B5 / 100 | D23: =C23 * Parâmetros!B12 / 100 | E23: =Parâmetros!B14 + Parâmetros!B15 | F23: 0 | G23: =IF(F23>0, F23 * Parâmetros!B8 / 100, 0) | H23: =G23 * Parâmetros!B13 / 100 | I23: 0 | J23: =IF(F23>0, F23 - G23, 0) | K23: =B23 + J23 + Parâmetros!B3
A24: 23 | B24: =K23 + Parâmetros!B3 | C24: =B24 * Parâmetros!B5 / 100 | D24: =C24 * Parâmetros!B12 / 100 | E24: =Parâmetros!B14 + Parâmetros!B15 | F24: 0 | G24: =IF(F24>0, F24 * Parâmetros!B8 / 100, 0) | H24: =G24 * Parâmetros!B13 / 100 | I24: 0 | J24: =IF(F24>0, F24 - G24, 0) | K24: =B24 + J24 + Parâmetros!B3
A25: 24 | B25: =K24 + Parâmetros!B3 | C25: =B25 * Parâmetros!B5 / 100 | D25: =C25 * Parâmetros!B12 / 100 | E25: =Parâmetros!B14 + Parâmetros!B15 | F25: 0 | G25: =IF(F25>0, F25 * Parâmetros!B8 / 100, 0) | H25: =G25 * Parâmetros!B13 / 100 | I25: 0 | J25: =IF(F25>0, F25 - G25, 0) | K25: =B25 + J25 + Parâmetros!B3
A26: 25 | B26: =K25 + Parâmetros!B3 | C26: =B26 * Parâmetros!B5 / 100 | D26: =C26 * Parâmetros!B12 / 100 | E26: =Parâmetros!B14 + Parâmetros!B15 | F26: 0 | G26: =IF(F26>0, F26 * Parâmetros!B8 / 100, 0) | H26: =G26 * Parâmetros!B13 / 100 | I26: 0 | J26: =IF(F26>0, F26 - G26, 0) | K26: =B26 + J26 + Parâmetros!B3
A27: 26 | B27: =K26 + Parâmetros!B3 | C27: =B27 * Parâmetros!B5 / 100 | D27: =C27 * Parâmetros!B12 / 100 | E27: =Parâmetros!B14 + Parâmetros!B15 | F27: 0 | G27: =IF(F27>0, F27 * Parâmetros!B8 / 100, 0) | H27: =G27 * Parâmetros!B13 / 100 | I27: 0 | J27: =IF(F27>0, F27 - G27, 0) | K27: =B27 + J27 + Parâmetros!B3
A28: 27 | B28: =K27 + Parâmetros!B3 | C28: =B28 * Parâmetros!B5 / 100 | D28: =C28 * Parâmetros!B12 / 100 | E28: =Parâmetros!B14 + Parâmetros!B15 | F28: 0 | G28: =IF(F28>0, F28 * Parâmetros!B8 / 100, 0) | H28: =G28 * Parâmetros!B13 / 100 | I28: 0 | J28: =IF(F28>0, F28 - G28, 0) | K28: =B28 + J28 + Parâmetros!B3
A29: 28 | B29: =K28 + Parâmetros!B3 | C29: =B29 * Parâmetros!B5 / 100 | D29: =C29 * Parâmetros!B12 / 100 | E29: =Parâmetros!B14 + Parâmetros!B15 | F29: 0 | G29: =IF(F29>0, F29 * Parâmetros!B8 / 100, 0) | H29: =G29 * Parâmetros!B13 / 100 | I29: 0 | J29: =IF(F29>0, F29 - G29, 0) | K29: =B29 + J29 + Parâmetros!B3
A30: 29 | B30: =K29 + Parâmetros!B3 | C30: =B30 * Parâmetros!B5 / 100 | D30: =C30 * Parâmetros!B12 / 100 | E30: =Parâmetros!B14 + Parâmetros!B15 | F30: 0 | G30: =IF(F30>0, F30 * Parâmetros!B8 / 100, 0) | H30: =G30 * Parâmetros!B13 / 100 | I30: 0 | J30: =IF(F30>0, F30 - G30, 0) | K30: =B30 + J30 + Parâmetros!B3
A31: 30 | B31: =K30 + Parâmetros!B3 | C31: =B31 * Parâmetros!B5 / 100 | D31: =C31 * Parâmetros!B12 / 100 | E31: =Parâmetros!B14 + Parâmetros!B15 | F31: 0 | G31: =IF(F31>0, F31 * Parâmetros!B8 / 100, 0) | H31: =G31 * Parâmetros!B13 / 100 | I31: 0 | J31: =IF(F31>0, F31 - G31, 0) | K31: =B31 + J31 + Parâmetros!B3

Sheet Comparativo
A1: Item | B1: Pessoa Física | C1: Pessoa Jurídica | D1: Diferença Absoluta | E1: Diferença %
A2: Patrimônio Bruto Final | B2: =Cálculo PF!H31 | C2: =Cálculo PJ!K31 + SUM(Cálculo PJ!I2:I31) | D2: 0 | E2: =IF(B2=0,0,D2/B2*100)
A3: Carga Tributária Acumulada | B3: =SUM(Cálculo PF!D2:D31) + SUM(Cálculo PF!E2:E31) | C3: =SUM(Cálculo PJ!D2:D31) + SUM(Cálculo PJ!H2:H31) | D3: 0 | E3: =IF(B3=0,0,D3/B3*100)
A4: Taxa Efetiva Total (%) | B4: =IF(SUM(Cálculo PF!C2:C31)=0,0,B3/SUM(Cálculo PF!C2:C31)*100) | C4: =IF(SUM(Cálculo PJ!C2:C31)=0,0,C3/SUM(Cálculo PJ!C2:C31)*100)
A5: Total Aportes | B5: =Parâmetros!B2 + Parâmetros!B3 * Parâmetros!B4 | C5: =Parâmetros!B2 + Parâmetros!B3 * Parâmetros!B4
A6: Ganho de Capital Bruto | B6: 0 | C6: 0
A7: Imposto sobre Ganho de Capital | B7: =IF(B6>0,B6*Parâmetros!B17/100,0) | C7: =IF(C6>0,C6*Parâmetros!B18/100,0)
A8: ITCMD | B8: =B2 * Parâmetros!B16 / 100 | C8: =C2 * Parâmetros!B16 / 100
A9: Patrimônio Líquido Final Após Impostos | B9: 0 | C9: 0 | D9: 0 | E9: =IF(B9=0,0,D9/B9*100)
A10: Recomendação | B10: =IF(B9>C9,"Melhor em PF",IF(C9>B9,"Melhor em PJ","Indiferente"))

Sheet Sensibilidade
A1: Cenário | B1: Valor 1 | C1: Valor 2 | D1: Valor 3 | E1: Valor 4
A2: Sensibilidade à Taxa de Retorno - Horizonte 30 anos, outros parâmetros base
A3: Taxa (%) | B3: Patrimônio Final PF (R$) | C3: Patrimônio Final PJ (R$) | D3: Diferença (R$) | E3: Diferença %
A4: 5 | B4: 3243398 | C4: 1000000 | D4: -2243398 | E4: -69.17
A5: 7.5 | B5: 5743491 | C5: 1000000 | D5: -4743491 | E5: -82.59
A6: 10 | B6: 10062657 | C6: 1000000 | D6: -9062657 | E6: -90.06
A7: 12.5 | B7: 17449402 | C7: 1715881 | D7: -15733521 | E7: -90.17
A8: 15 | B8: 29959922 | C8: 2910265 | D8: -27049657 | E8: -90.29
A10: Sensibilidade ao Horizonte - Taxa 10%, outros parâmetros base
A11: Anos | B11: Patrimônio Final PF (R$) | C11: Patrimônio Final PJ (R$) | D11: Diferença (R$) | E11: Diferença %
A12: 10 | B12: 2158925 | C12: 1000000 | D12: -1158925 | E12: -53.68
A13: 15 | B13: 3172169 | C13: 1000000 | D13: -2172169 | E13: -68.48
A14: 20 | B14: 4660957 | C14: 1000000 | D14: -3660957 | E14: -78.55
A15: 25 | B15: 6848475 | C15: 1000000 | D15: -5848475 | E15: -85.4
A16: 30 | B16: 10062657 | C16: 1000000 | D16: -9062657 | E16: -90.06
A18: Sensibilidade à Alíquota Efetiva PJ - Taxa 10%, Horizonte 30 anos, outros base
A19: Alíquota PJ (%) | B19: Patrimônio Final PF (R$) | C19: Patrimônio Final PJ (R$) | D19: Diferença (R$) | E19: Diferença %
A20: 25 | B20: 10062657 | C20: 1268996 | D20: -8793661 | E20: -87.39
A21: 30 | B21: 10062657 | C21: 1000000 | D21: -9062657 | E21: -90.06
A22: 34 | B22: 10062657 | C22: 1000000 | D22: -9062657 | E22: -90.06
A23: 40 | B23: 10062657 | C23: 1000000 | D23: -9062657 | E23: -90.06
